aeroshield/__init__.py
aeroshield/aeroshield/__init__.py
aeroshield/aeroshield/aeroshield.py
aeroshield/aeroshield/dummy.py
aeroshield/aeroshield/exception.py
aeroshield/controller.py
aeroshield/plotting/__init__.py
aeroshield/plotting/live_plotter.py
aeroshield/plotting/plotter.py
python_aeroshield-0.3.3.dist-info/LICENSE
python_aeroshield-0.3.3.dist-info/METADATA
python_aeroshield-0.3.3.dist-info/WHEEL
python_aeroshield-0.3.3.dist-info/RECORD
