Metadata-Version: 2.1
Name: python-aeroshield
Version: 0.3.3
Summary: A Python interface to AutomationShield's AeroShield Arduino shield
Home-page: https://gitlab.com/mrtreasurer/python-aeroshield
License: MIT
Author: Bert Van den Abbeele
Requires-Python: >=3.10
Classifier: License :: OSI Approved :: MIT License
Classifier: Programming Language :: Python :: 3
Classifier: Programming Language :: Python :: 3.10
Classifier: Programming Language :: Python :: 3.11
Classifier: Programming Language :: Python :: 3.12
Requires-Dist: matplotlib (>=3.8.2)
Requires-Dist: numpy (>=1.26.3)
Requires-Dist: pyserial (>=3.5)
Project-URL: Documentation, https://python-aeroshield.readthedocs.io
Project-URL: Repository, https://gitlab.com/mrtreasurer/python-aeroshield
